score.geoip-0.2.3-py3.4-nspkg.pth
score/geoip/__init__.py
score/geoip/_init.py
score/geoip/backend.py
score/geoip/cli.py
score.geoip-0.2.3.dist-info/DESCRIPTION.rst
score.geoip-0.2.3.dist-info/METADATA
score.geoip-0.2.3.dist-info/RECORD
score.geoip-0.2.3.dist-info/WHEEL
score.geoip-0.2.3.dist-info/entry_points.txt
score.geoip-0.2.3.dist-info/metadata.json
score.geoip-0.2.3.dist-info/namespace_packages.txt
score.geoip-0.2.3.dist-info/top_level.txt
