Metadata-Version: 2.0
Name: score.geoip
Version: 0.2.3
Summary: IP Geolocalization for The SCORE Framework
Home-page: http://strg.at
Author: strg.at
Author-email: support@strg.at
License: LGPL
Keywords: web wsgi bfg pylons pyramid
Platform: UNKNOWN
Classifier: Development Status :: 4 - Beta
Classifier: Environment :: Console
Classifier: Environment :: Web Environment
Classifier: Framework :: Pyramid
Classifier: Intended Audience :: Developers
Classifier: License :: OSI Approved :: GNU Lesser General Public License v3 or later (LGPLv3+)
Classifier: Operating System :: OS Independent
Classifier: Programming Language :: Python :: 3
Classifier: Programming Language :: Python :: 3.4
Classifier: Programming Language :: Python :: 3.5
Classifier: Topic :: Software Development :: Libraries :: Application Frameworks
Requires-Dist: dnspython3
Requires-Dist: score.init (>=0.3)
